RoboCupDBA_RAI/__init__.py
RoboCupDBA_RAI/config.py
RoboCupDBA_RAI/insert.py
RoboCupDBA_RAI/query.py
RoboCupDBA_RAI-0.1.dist-info/LICENSE.txt
RoboCupDBA_RAI-0.1.dist-info/METADATA
RoboCupDBA_RAI-0.1.dist-info/WHEEL
RoboCupDBA_RAI-0.1.dist-info/top_level.txt
RoboCupDBA_RAI-0.1.dist-info/RECORD
